XMLtoCSV/XMLtoCSVConvert.py
HLKLogParser-2.0.0.dist-info/LICENSE.txt
HLKLogParser-2.0.0.dist-info/METADATA
HLKLogParser-2.0.0.dist-info/WHEEL
HLKLogParser-2.0.0.dist-info/top_level.txt
HLKLogParser-2.0.0.dist-info/RECORD
