Metadata-Version: 2.1
Name: HLKLogParser
Version: 2.0.0
Summary: Conversion of HLK Xml format logs to CSV format
Home-page: UNKNOWN
Author: Komal
Author-email: komalpreetx.kaur@intel.com
License: Commercial
Platform: UNKNOWN
Requires-Dist: pandas
Requires-Dist: cryptography
Requires-Dist: mysql.connector
Requires-Dist: Fernet
Requires-Dist: sqlalchemy
